ManualTB/rtl/fsm.sv
`timescale 1ns/1ns
`define N 10 // delay of beverages delivering
`define M 20 // delay of change delivering

module Fsm (clk, rst, coin_in, button_in, change_out, beverage_out);
input clk, rst, coin_in, button_in;
output change_out, beverage_out;

logic [2:0] state;
reg[15:0] c;							// Money counter

reg[15:0] coin_in;						// ASSUMPTION: At the beginnning coin_in = X
//reg[15:0] coin;
reg[1:0] button_in;						
reg[15:0] change_out;					// ASSUMPTION: At the beginning change_out = X
reg[1:0] beverage_out;

localparam add_coin = 3'b000; 			// Initial state
localparam water = 3'b001;
localparam soda = 3'b010;
localparam change = 3'b011;
localparam credit0 = 3'b100;

parameter N = 10;
parameter M = 20;

always_ff @(posedge clk or rst) begin
    if(rst)begin
    	c <= 16'd0;
    	beverage_out <= 2'b00;
    	state <= add_coin;
    end else begin
    	case (state)
			add_coin: begin
        	// ASSUMPTION: Once the coin is in, there is no going back.
				if(c >= 16'd30 && button_in==2'b01) begin 					// User has chosen WATER
					#`N state <= water;
				end else if(c >= 16'd50 && button_in==2'b11) begin			// User has chosen SODA
					#`N state <= soda;
				end else if(button_in == 2'b00 &&							// User is accumulating MONEY
					(coin_in == 16'd10 ||coin_in == 16'd20 ||coin_in == 16'd50 ||coin_in == 16'd100 ||coin_in == 16'd200))begin
					c <= c + coin_in;
					state <= add_coin;
				end else begin
					state <= add_coin; // Machine ignores every non-admissible input.
				end
			end
        	water: begin
        		c <= c - 16'd30;
        		beverage_out <= 2'b01;
        		state <= change;
        	end
        	soda: begin
        		c <= c - 16'd50;
        		beverage_out <= 2'b11;
        		state <= change;
        	end
			change: begin
				beverage_out <= 2'b00;
				if(c < 16'd30) begin
					#`M change_out <= c;
					state <= credit0;
				end else begin
					state <= add_coin;
				end
			end
			credit0: begin
				c <= 16'd0;
				state <= add_coin;
				change_out <= 16'd0;
			end
    	endcase
    end
end 
endmodule

Part_1/tb/tb.sv
`timescale 1ns/1ns
`define N 10 // Delay of beverages delivery
`define M 20 // Delay of change delivery

module test;
  logic clk, rst;
  reg[15:0] coin_in;
  reg[1:0] button_in;
  reg[1:0] beverage_out;
  reg[15:0] change_out;
  
  Fsm fsm(.clk(clk),
          .rst(rst),
          .coin_in(coin_in),
          .button_in(button_in),
          .change_out(change_out),
          .beverage_out(beverage_out));
          
  always
    begin
      #5 clk =~clk;
    end

  initial begin
    $dumpfile("fsm.vcd");
    $dumpvars(0,test);
    clk = 0;
    rst = 1;
    button_in = 00; // Define the signal coming from the buttons
    #10;
    rst = 0;
    #10;
    coin_in = 200;
    #10;
    coin_in = 0;
    #10;
    coin_in = 20;
    #10;
    coin_in = 0;
    #20;
    button_in = 10; // Anomaly: Illegal button code
    #`N
    #10;
    button_in = 00;
    #30;
    button_in = 11;
    #`N
    #10;
    button_in = 00;
    #40;
    button_in = 11;
    #`N
    #10;
    button_in = 00;
    #50;
    button_in = 01;
    #`N
    #10;
    button_in = 00;
    #40;
    button_in = 01;
    #`N;
    #`M;
    #10;
    button_in = 00;
    #60;
    coin_in = 20;
    #10;
    coin_in = 0;
    #10;
    button_in = 01;
    #30;
    button_in = 00;
    #40;
    button_in = 01;
    #10;
    #`N;
    #`M;
    coin_in = 10; // <- Anomaly: The user is inserting a coin during a delivery BUT the machine ignores the request.
    #10;
    button_in = 00;
    #10;
    coin_in = 0;
    #`N;
    button_in = 00;
    #200;
    $finish;
  end
endmodule

ManualTB/fsm.vcd
$date
	Wed Dec 28 15:53:48 2022
$end
$version
	ModelSim Version 2019.4
$end
$timescale
	1ns
$end

$scope module test $end
$var reg 1 ! clk $end
$var reg 1 " rst $end
$var reg 16 # coin_in [15:0] $end
$var reg 2 $ button_in [1:0] $end
$var reg 2 % beverage_out [1:0] $end
$var reg 16 & change_out [15:0] $end

$scope module fsm $end
$var parameter 3 ' add_coin $end
$var parameter 3 ( water $end
$var parameter 3 ) soda $end
$var parameter 3 * change $end
$var parameter 3 + credit0 $end
$var parameter 32 , N $end
$var parameter 32 - M $end
$var wire 1 . clk $end
$var wire 1 / rst $end
$var reg 16 0 coin_in [15:0] $end
$var reg 2 1 button_in [1:0] $end
$var reg 16 2 change_out [15:0] $end
$var reg 2 3 beverage_out [1:0] $end
$var reg 3 4 state [2:0] $end
$var reg 16 5 c [15:0] $end
$upscope $end
$upscope $end
$enddefinitions $end
#0
$dumpvars
0!
1"
bx #
b0 $
b0 %
bx &
bx 0
b0 1
bx 2
b0 3
b0 4
b0 5
b0 '
b1 (
b10 )
b11 *
b100 +
b1010 ,
b10100 -
1/
0.
$end
#5
1!
1.
#10
0"
0!
0/
0.
#15
1!
1.
#20
b11001000 #
0!
b11001000 0
0.
#25
1!
1.
b11001000 5
#30
b0 #
0!
b0 0
0.
#35
1!
1.
#40
b10100 #
0!
b10100 0
0.
#45
1!
1.
b11011100 5
#50
b0 #
0!
b0 0
0.
#55
1!
1.
#60
0!
0.
#65
1!
1.
#70
b10 $
0!
b10 1
0.
#75
1!
1.
#80
0!
0.
#85
1!
1.
#90
b0 $
0!
b0 1
0.
#95
1!
1.
#100
0!
0.
#105
1!
1.
#110
0!
0.
#115
1!
1.
#120
b11 $
0!
b11 1
0.
#125
1!
1.
#130
0!
0.
#135
1!
1.
b10 4
#140
b0 $
0!
b0 1
0.
#145
1!
1.
b10101010 5
b11 3
b11 4
b11 %
#150
0!
0.
#155
1!
1.
b0 3
b0 4
b0 %
#160
0!
0.
#165
1!
1.
#170
0!
0.
#175
1!
1.
#180
b11 $
0!
b11 1
0.
#185
1!
1.
#190
0!
0.
#195
1!
1.
b10 4
#200
b0 $
0!
b0 1
0.
#205
1!
1.
b1111000 5
b11 3
b11 4
b11 %
#210
0!
0.
#215
1!
1.
b0 3
b0 4
b0 %
#220
0!
0.
#225
1!
1.
#230
0!
0.
#235
1!
1.
#240
0!
0.
#245
1!
1.
#250
b1 $
0!
b1 1
0.
#255
1!
1.
#260
0!
0.
#265
1!
1.
b1 4
#270
b0 $
0!
b0 1
0.
#275
1!
1.
b1011010 5
b1 3
b11 4
b1 %
#280
0!
0.
#285
1!
1.
b0 3
b0 4
b0 %
#290
0!
0.
#295
1!
1.
#300
0!
0.
#305
1!
1.
#310
b1 $
0!
b1 1
0.
#315
1!
1.
#320
0!
0.
#325
1!
1.
b1 4
#330
0!
0.
#335
1!
1.
b111100 5
b1 3
b11 4
b1 %
#340
0!
0.
#345
1!
1.
b0 3
b0 4
b0 %
#350
b0 $
0!
b0 1
0.
#355
1!
1.
#360
0!
0.
#365
1!
1.
#370
0!
0.
#375
1!
1.
#380
0!
0.
#385
1!
1.
#390
0!
0.
#395
1!
1.
#400
0!
0.
#405
1!
1.
#410
b10100 #
0!
b10100 0
0.
#415
1!
1.
b1010000 5
#420
b0 #
0!
b0 0
0.
#425
1!
1.
#430
b1 $
0!
b1 1
0.
#435
1!
1.
#440
0!
0.
#445
1!
1.
b1 4
#450
0!
0.
#455
1!
1.
b110010 5
b1 3
b11 4
b1 %
#460
b0 $
0!
b0 1
0.
#465
1!
1.
b0 3
b0 4
b0 %
#470
0!
0.
#475
1!
1.
#480
0!
0.
#485
1!
1.
#490
0!
0.
#495
1!
1.
#500
b1 $
0!
b1 1
0.
#505
1!
1.
#510
0!
0.
#515
1!
1.
b1 4
#520
0!
0.
#525
1!
1.
b10100 5
b1 3
b11 4
b1 %
#530
0!
0.
#535
1!
1.
b0 3
b0 %
#540
b1010 #
0!
b1010 0
0.
#545
1!
1.
#550
b0 $
0!
b0 1
0.
#555
1!
1.
b10100 2
b100 4
b10100 &
#560
b0 #
0!
b0 0
0.
#565
1!
1.
#570
0!
0.
#575
1!
1.
b0 5
b0 4
b0 2
b0 &
